Metadata-Version: 2.1
Name: alex-nn
Version: 0.1.11
Summary: Network analysis
Home-page: https://github.com/yinan16/alex
Author: Yinan Yu
Author-email: yu.yinan16@gmail.com
License: UNKNOWN
Project-URL: Bug Tracker, https://github.com/yinan16/alex/issues
Platform: UNKNOWN
Classifier: Programming Language :: Python :: 3
Requires-Python: >=3.6
Requires-Dist: pandas
Requires-Dist: numpy
Requires-Dist: pydot (==1.4.1)
Requires-Dist: pyparsing
Requires-Dist: scikit-learn (==0.23.2)
Requires-Dist: PyYAML (>=5.4)
Requires-Dist: jsonschema
Requires-Dist: rope
Requires-Dist: matplotlib
